{
  "db_name": "PostgreSQL",
  "query": "\n            INSERT INTO organization_alerts_active (\n                alert_id,\n                organization_id,\n                created_at,\n                alert_data\n            )\n            VALUES ($1, $2, $3, $4)\n            ",
  "describe": {
    "columns": [],
    "parameters": {
      "Left": [
        "Uuid",
        "Int8",
        "Timestamp",
        "Jsonb"
      ]
    },
    "nullable": []
  },
  "hash": "27af37925e4d0dfc4b754968ef0289bc23bc0101dbf906174ea731f68da9c2c9"
}
