{
  "db_name": "PostgreSQL",
  "query": "\n            SELECT\n                alert_id,\n                organization_id,\n                created_at,\n                alert_data\n            FROM organization_alerts_active\n            WHERE organization_id = $1\n            ",
  "describe": {
    "columns": [
      {
        "ordinal": 0,
        "name": "alert_id",
        "type_info": "Uuid"
      },
      {
        "ordinal": 1,
        "name": "organization_id",
        "type_info": "Int8"
      },
      {
        "ordinal": 2,
        "name": "created_at",
        "type_info": "Timestamp"
      },
      {
        "ordinal": 3,
        "name": "alert_data",
        "type_info": "Jsonb"
      }
    ],
    "parameters": {
      "Left": [
        "Int8"
      ]
    },
    "nullable": [
      false,
      false,
      false,
      false
    ]
  },
  "hash": "c86c3bb73a369279bffb4792d11f81c4022c59328dd8ddabeb41478be092fb5d"
}
